databricks_cicd/__init__.py
databricks_cicd/cli.py
databricks_cicd/conf/__init__.py
databricks_cicd/conf/conf.py
databricks_cicd/conf/default.ini
databricks_cicd/deploy/__init__.py
databricks_cicd/deploy/cli.py
databricks_cicd/utils/__init__.py
databricks_cicd/utils/api.py
databricks_cicd/utils/helpers.py
databricks_cicd/utils/local.py
databricks_cicd/validate/__init__.py
databricks_cicd/validate/cli.py
tactivos_databricks_cicd-0.1.16.dist-info/LICENSE
tactivos_databricks_cicd-0.1.16.dist-info/METADATA
tactivos_databricks_cicd-0.1.16.dist-info/WHEEL
tactivos_databricks_cicd-0.1.16.dist-info/entry_points.txt
tactivos_databricks_cicd-0.1.16.dist-info/top_level.txt
tactivos_databricks_cicd-0.1.16.dist-info/RECORD
