Metadata-Version: 2.1
Name: tactivos-databricks-cicd
Version: 0.1.16
Summary: CICD tool for testing and deploying to Databricks
Home-page: https://github.com/tactivos/databricks-cicd
Author: Manol Manolov - Minor changes from Kevin Gould (Mural)
Author-email: 
License: Apache License 2.0
Project-URL: Source, https://github.com/tactivos/databricks-cicd
Keywords: databricks cicd
Classifier: Intended Audience :: Developers
Classifier: Intended Audience :: System Administrators
Classifier: Programming Language :: Python :: 3.6
License-File: LICENSE
Requires-Dist: requests (>=2.28.1)
Requires-Dist: click (>=6.7)
